notification.py
setup.py
mulaptested_pakname.egg-info/PKG-INFO
mulaptested_pakname.egg-info/SOURCES.txt
mulaptested_pakname.egg-info/dependency_links.txt
mulaptested_pakname.egg-info/top_level.txt