Metadata-Version: 2.1
Name: mulaptested-pakname
Version: 1.0.0
Summary: Safe POC for typo squatting/dependency confusion testing
Author: Your Name
License: MIT
